vcf2pandas/__init__.py
vcf2pandas/vcf2pandas.py
vcf2pandas-0.2.0.dist-info/LICENSE
vcf2pandas-0.2.0.dist-info/METADATA
vcf2pandas-0.2.0.dist-info/WHEEL
vcf2pandas-0.2.0.dist-info/RECORD
