Metadata-Version: 2.3
Name: vcf2pandas
Version: 0.2.0
Summary: Package to convert a vcf into a pandas dataframe.
License: MIT
Keywords: vcf,python,pandas
Author: Trent Zeng
Requires-Python: >=3.10,<4.0
Classifier: License :: OSI Approved :: MIT License
Classifier: Programming Language :: Python :: 3
Classifier: Programming Language :: Python :: 3.10
Classifier: Programming Language :: Python :: 3.11
Classifier: Programming Language :: Python :: 3.12
Classifier: Programming Language :: Python :: 3.13
Requires-Dist: pandas (>=2.1.0,<3.0.0)
Requires-Dist: pysam (>=0.22.1,<0.23.0)
Requires-Dist: pytest (>=8.3.5,<9.0.0)
Project-URL: Repository, https://github.com/trentzz/vcf2pandas
